[
    {
        "image": "https://example.com/images/match1.jpg",
        "title": "Match 1: Team A vs Team B",
        "link": "https://example.com/highlights/match1"
    },
    {
        "image": "https://example.com/images/match2.jpg",
        "title": "Match 2: Team C vs Team D",
        "link": "https://example.com/highlights/match2"
    },
    {
        "image": "https://example.com/images/match3.jpg",
        "title": "Match 3: Team E vs Team F",
        "link": "https://example.com/highlights/match3"
    }
]
